{
  "id": 91798,
  "institutionId": 1660,
  "parentOrganizationId": null,
  "branchId": null,
  "name": "Arnold Air Society",
  "shortName": "Arnies",
  "websiteKey": "arnoldairsociety",
  "profilePicture": "be4dbaa2-9de4-426d-aaf6-4bf228f4ded89767bb88-d9e2-44df-aedc-e759dd7e026a.jpg",
  "profilePictureURL": "https://se-images.campuslabs.com/clink/images/be4dbaa2-9de4-426d-aaf6-4bf228f4ded89767bb88-d9e2-44df-aedc-e759dd7e026a.jpg",
  "description": "\u003cp\u003eThe Arnold Air Society is a professional, honorary, service organization advocating the support of aerospace power.\u003c/p\u003e",
  "summary": "To provides opportunities for U.S. Air Force officer candidates to participate in campus and community service activities, demonstrating the close relationship between civilian and military institutions.",
  "categoryIds": [
    "2693",
    "5115",
    "7850",
    "9415"
  ],
  "categoryNames": [
    "ASUC Sponsored 2025-26-Student Activity Groups",
    "Professional Student Organizations",
    "Undergraduate Organizations",
    "ABSA-Allocated Hearst Storage "
  ],
  "status": "Active",
  "visibility": "Public",
  "email": "alanyan10@berkeley.edu",
  "communityId": 219,
  "nameSortKey": "A",
  "comment": null,
  "showJoin": false,
  "statusChangeDateTime": "2016-03-01T16:05:22-05:00",
  "startDate": "2013-07-29T00:00:00-04:00",
  "endDate": null,
  "parentId": 45852,
  "wallId": null,
  "discussionId": 1334122,
  "groupTypeId": null,
  "organizationTypeId": 1243,
  "cssConfigurationId": null,
  "deleted": false,
  "enableGoogleCalendar": false,
  "modifiedOn": "2024-11-08T14:22:50-05:00",
  "showFacebookWall": false,
  "showTwitterFeed": false,
  "isShownInPublicDirectory": true,
  "isAdminOnly": false,
  "isBranch": false,
  "legacyKey": null,
  "parentLegacyKey": null,
  "legacyPrimaryContactKey": null,
  "socialMedia": {
    "externalWebsite": "",
    "facebookUrl": "https://www.facebook.com/Arnold-Air-Society-Berkeley-Detachment-Fundraisers-672384216265808/",
    "twitterUrl": "",
    "twitterUserName": null,
    "instagramUrl": "https://www.instagram.com/doolittlesquadron/?hl=en",
    "linkedInUrl": "",
    "youtubeUrl": "",
    "flickrUrl": "",
    "googleCalendarUrl": "",
    "googlePlusUrl": "",
    "pinterestUrl": "",
    "tumblrUrl": "",
    "vimeoUrl": ""
  },
  "primaryContact": {
    "id": "252d3c9b-aa36-4238-a064-88d8315bfc97",
    "firstName": "Alan",
    "lastName": "Yan",
    "preferredFirstName": null,
    "primaryEmailAddress": "alanyan10@berkeley.edu",
    "profileImageFilePath": null,
    "institutionId": 1660,
    "privacy": "Unselected"
  },
  "primaryContactId": {
    "communityMemberId": 34866564,
    "accountId": "252d3c9b-aa36-4238-a064-88d8315bfc97",
    "campusEmail": "alanyan10@berkeley.edu"
  },
  "contactInfo": [
    {
      "id": 169154,
      "addressType": 0,
      "phoneNumber": null,
      "extension": null,
      "faxNumber": null,
      "street1": "176 Hearst Gym ",
      "street2": null,
      "city": "Berkeley",
      "state": "CA",
      "zip": "94720",
      "country": "United States",
      "deleted": false
    }
  ],
  "organizationType": {
    "id": 1243,
    "branchId": 45852,
    "name": "Registered Student Organizations",
    "showMembersToPublic": false,
    "showOfficersToPublic": false,
    "showMembersToLoggedInUsersByDefault": false,
    "showOfficersToLoggedInUsersByDefault": false,
    "autoApproveRequests": false,
    "eventsEnabled": true,
    "serviceHoursEnabled": true,
    "financeEnabled": true,
    "financeRequestsEnabled": true,
    "fundingRequestsEnabled": true,
    "purchaseRequestsEnabled": true,
    "budgetingEnabled": false,
    "budgetingRequestsEnabled": false,
    "electionsEnabled": true,
    "formsEnabled": true,
    "galleryEnabled": true,
    "outcomesEnabled": true,
    "rosterEnabled": true,
    "documentsEnabled": true,
    "shownInPublicDirectory": true,
    "isSystemType": false,
    "adminOnly": false,
    "isClosed": false,
    "reRegistrationAvailabilty": null
  },
  "categories": [],
  "submissions": [],
  "coverPhoto": {
    "id": 0,
    "imageId": "",
    "imagePath": "",
    "url": "",
    "thumbnailUrl": "",
    "caption": "",
    "dateCreated": "",
    "institutionId": 0
  },
  "imageServerBaseUrl": "",
  "baseUrl": "https://callink.berkeley.edu"
}