{
  "id": 46415,
  "institutionId": 1660,
  "parentOrganizationId": null,
  "branchId": null,
  "name": "Statistics Graduate Students Association",
  "shortName": "SGSA",
  "websiteKey": "gastatisticsgraduatestudentassociation",
  "profilePicture": "18f0b74d-0ced-4378-a45f-35d703be5dea83828ba7-7463-4084-b624-6bf069172511.png",
  "profilePictureURL": "https://se-images.campuslabs.com/clink/images/18f0b74d-0ced-4378-a45f-35d703be5dea83828ba7-7463-4084-b624-6bf069172511.png",
  "description": "",
  "summary": "Our purpose is to safeguard the interests of graduate students in statistics and biostatistics, to serve as the formal link between students and faculty, and to organize social events for students or for students and faculty.",
  "categoryIds": [
    "5105"
  ],
  "categoryNames": [
    "Graduate Student Organizations "
  ],
  "status": "Active",
  "visibility": "Public",
  "email": "sgsa-stat@berkeley.edu",
  "communityId": 219,
  "nameSortKey": "S",
  "comment": null,
  "showJoin": false,
  "statusChangeDateTime": "",
  "startDate": "1969-12-31T00:00:00-05:00",
  "endDate": null,
  "parentId": 45852,
  "wallId": null,
  "discussionId": 77984,
  "groupTypeId": null,
  "organizationTypeId": 1243,
  "cssConfigurationId": null,
  "deleted": false,
  "enableGoogleCalendar": false,
  "modifiedOn": "2024-07-27T00:43:19-04:00",
  "showFacebookWall": false,
  "showTwitterFeed": false,
  "isShownInPublicDirectory": true,
  "isAdminOnly": false,
  "isBranch": false,
  "legacyKey": 27358,
  "parentLegacyKey": null,
  "legacyPrimaryContactKey": null,
  "socialMedia": {
    "externalWebsite": "http://statistics.berkeley.edu/resources/sgsa",
    "facebookUrl": "",
    "twitterUrl": "",
    "twitterUserName": null,
    "instagramUrl": "",
    "linkedInUrl": "",
    "youtubeUrl": "",
    "flickrUrl": "",
    "googleCalendarUrl": "",
    "googlePlusUrl": "",
    "pinterestUrl": "",
    "tumblrUrl": "",
    "vimeoUrl": ""
  },
  "primaryContact": {
    "id": "649127eb-f58f-4792-b996-16ad66c4786e",
    "firstName": "Joao Vitor",
    "lastName": "Romano",
    "preferredFirstName": null,
    "primaryEmailAddress": "jv.romano@berkeley.edu",
    "profileImageFilePath": null,
    "institutionId": 1660,
    "privacy": "Unselected"
  },
  "primaryContactId": {
    "communityMemberId": 38414617,
    "accountId": "649127eb-f58f-4792-b996-16ad66c4786e",
    "campusEmail": "jv.romano@berkeley.edu"
  },
  "contactInfo": [
    {
      "id": 139916,
      "addressType": 0,
      "phoneNumber": null,
      "extension": null,
      "faxNumber": null,
      "street1": "367 Evans Hall",
      "street2": "University of California, Berkeley",
      "city": "Berkeley",
      "state": "CA",
      "zip": "94720",
      "country": "United States",
      "deleted": false
    }
  ],
  "organizationType": {
    "id": 1243,
    "branchId": 45852,
    "name": "Registered Student Organizations",
    "showMembersToPublic": false,
    "showOfficersToPublic": false,
    "showMembersToLoggedInUsersByDefault": false,
    "showOfficersToLoggedInUsersByDefault": false,
    "autoApproveRequests": false,
    "eventsEnabled": true,
    "serviceHoursEnabled": true,
    "financeEnabled": true,
    "financeRequestsEnabled": true,
    "fundingRequestsEnabled": true,
    "purchaseRequestsEnabled": true,
    "budgetingEnabled": false,
    "budgetingRequestsEnabled": false,
    "electionsEnabled": true,
    "formsEnabled": true,
    "galleryEnabled": true,
    "outcomesEnabled": true,
    "rosterEnabled": true,
    "documentsEnabled": true,
    "shownInPublicDirectory": true,
    "isSystemType": false,
    "adminOnly": false,
    "isClosed": false,
    "reRegistrationAvailabilty": null
  },
  "categories": [],
  "submissions": [],
  "coverPhoto": {
    "id": 0,
    "imageId": "",
    "imagePath": "",
    "url": "",
    "thumbnailUrl": "",
    "caption": "",
    "dateCreated": "",
    "institutionId": 0
  },
  "imageServerBaseUrl": "",
  "baseUrl": "https://callink.berkeley.edu"
}