{
  "id": 46090,
  "institutionId": 1660,
  "parentOrganizationId": null,
  "branchId": null,
  "name": "UC Jazz Ensemble",
  "shortName": "UCJE",
  "websiteKey": "ucjazz",
  "profilePicture": "12f569e5-08ca-4994-b52f-43e95190f7efea103a31-d9bc-4a3f-8e41-09f058b38f21.jpg",
  "profilePictureURL": "https://se-images.campuslabs.com/clink/images/12f569e5-08ca-4994-b52f-43e95190f7efea103a31-d9bc-4a3f-8e41-09f058b38f21.jpg",
  "description": "\u003cp\u003eUC Jazz Ensembles is the primary source for jazz performance opportunities on campus, open to students of all majors.\u003c/p\u003e",
  "summary": "UC Jazz is the primary source for jazz performance opportunities on campus, open to students of all majors.",
  "categoryIds": [
    "2693",
    "5113",
    "7850"
  ],
  "categoryNames": [
    "ASUC Sponsored 2025-26-Student Activity Groups",
    "Performing Arts Student Organizations",
    "Undergraduate Organizations"
  ],
  "status": "Active",
  "visibility": "Public",
  "email": "tmoore@ucjazz.berkeley.edu",
  "communityId": 219,
  "nameSortKey": "U",
  "comment": null,
  "showJoin": false,
  "statusChangeDateTime": "",
  "startDate": "1969-12-31T00:00:00-05:00",
  "endDate": null,
  "parentId": 45852,
  "wallId": null,
  "discussionId": 77659,
  "groupTypeId": null,
  "organizationTypeId": 1243,
  "cssConfigurationId": null,
  "deleted": false,
  "enableGoogleCalendar": false,
  "modifiedOn": "2024-08-07T15:20:50-04:00",
  "showFacebookWall": false,
  "showTwitterFeed": false,
  "isShownInPublicDirectory": true,
  "isAdminOnly": false,
  "isBranch": false,
  "legacyKey": 19960,
  "parentLegacyKey": null,
  "legacyPrimaryContactKey": null,
  "socialMedia": {
    "externalWebsite": "http://ucjazz.berkeley.edu",
    "facebookUrl": "http://www.facebook.com/ucjazz",
    "twitterUrl": "",
    "twitterUserName": null,
    "instagramUrl": "https://www.instagram.com/ucjazz/",
    "linkedInUrl": "",
    "youtubeUrl": "https://www.youtube.com/@ucjazzensembles",
    "flickrUrl": "",
    "googleCalendarUrl": "",
    "googlePlusUrl": "",
    "pinterestUrl": "",
    "tumblrUrl": "",
    "vimeoUrl": ""
  },
  "primaryContact": {
    "id": "17cebabc-c542-4f47-8871-9b4cd1094236",
    "firstName": "Sam",
    "lastName": "Malekzadeh",
    "preferredFirstName": null,
    "primaryEmailAddress": "sam21malek@berkeley.edu",
    "profileImageFilePath": null,
    "institutionId": 1660,
    "privacy": "Unselected"
  },
  "primaryContactId": {
    "communityMemberId": 35907594,
    "accountId": "17cebabc-c542-4f47-8871-9b4cd1094236",
    "campusEmail": "sam21malek@berkeley.edu"
  },
  "contactInfo": [
    {
      "id": 191003,
      "addressType": 0,
      "phoneNumber": "510-642-5062",
      "extension": null,
      "faxNumber": null,
      "street1": "72 Cesar Chavez Student Center #4280",
      "street2": null,
      "city": "Berkeley",
      "state": "CA",
      "zip": "94720",
      "country": "United States",
      "deleted": false
    }
  ],
  "organizationType": {
    "id": 1243,
    "branchId": 45852,
    "name": "Registered Student Organizations",
    "showMembersToPublic": false,
    "showOfficersToPublic": false,
    "showMembersToLoggedInUsersByDefault": false,
    "showOfficersToLoggedInUsersByDefault": false,
    "autoApproveRequests": false,
    "eventsEnabled": true,
    "serviceHoursEnabled": true,
    "financeEnabled": true,
    "financeRequestsEnabled": true,
    "fundingRequestsEnabled": true,
    "purchaseRequestsEnabled": true,
    "budgetingEnabled": false,
    "budgetingRequestsEnabled": false,
    "electionsEnabled": true,
    "formsEnabled": true,
    "galleryEnabled": true,
    "outcomesEnabled": true,
    "rosterEnabled": true,
    "documentsEnabled": true,
    "shownInPublicDirectory": true,
    "isSystemType": false,
    "adminOnly": false,
    "isClosed": false,
    "reRegistrationAvailabilty": null
  },
  "categories": [],
  "submissions": [],
  "coverPhoto": {
    "id": 0,
    "imageId": "",
    "imagePath": "",
    "url": "",
    "thumbnailUrl": "",
    "caption": "",
    "dateCreated": "",
    "institutionId": 0
  },
  "imageServerBaseUrl": "",
  "baseUrl": "https://callink.berkeley.edu"
}