{
  "id": 91800,
  "institutionId": 1660,
  "parentOrganizationId": null,
  "branchId": null,
  "name": "Research Experience Pathways",
  "shortName": null,
  "websiteKey": "researchexperiencepathways",
  "profilePicture": "1b4b4d11-97df-485a-81d6-e3c47d2bdc400d6a015d-2d79-469a-a1f7-c4c8e4534c83.png",
  "profilePictureURL": "https://se-images.campuslabs.com/clink/images/1b4b4d11-97df-485a-81d6-e3c47d2bdc400d6a015d-2d79-469a-a1f7-c4c8e4534c83.png",
  "description": "",
  "summary": "The Research Experience Pathways program aims to increase access to research opportunities for underrepresented undergraduate students from low-income backgrounds by connecting students to paid research opportunities at UC Berkeley.",
  "categoryIds": [
    "5115",
    "7850"
  ],
  "categoryNames": [
    "Professional Student Organizations",
    "Undergraduate Organizations"
  ],
  "status": "Active",
  "visibility": "Public",
  "email": "",
  "communityId": 219,
  "nameSortKey": "R",
  "comment": null,
  "showJoin": false,
  "statusChangeDateTime": "2016-07-12T18:11:40-04:00",
  "startDate": "2013-07-29T00:00:00-04:00",
  "endDate": null,
  "parentId": 45852,
  "wallId": null,
  "discussionId": 1334124,
  "groupTypeId": null,
  "organizationTypeId": 1243,
  "cssConfigurationId": null,
  "deleted": false,
  "enableGoogleCalendar": false,
  "modifiedOn": "2025-02-28T21:11:35-05:00",
  "showFacebookWall": false,
  "showTwitterFeed": false,
  "isShownInPublicDirectory": true,
  "isAdminOnly": false,
  "isBranch": false,
  "legacyKey": null,
  "parentLegacyKey": null,
  "legacyPrimaryContactKey": null,
  "socialMedia": {
    "externalWebsite": "",
    "facebookUrl": "",
    "twitterUrl": "",
    "twitterUserName": null,
    "instagramUrl": "",
    "linkedInUrl": "",
    "youtubeUrl": "",
    "flickrUrl": "",
    "googleCalendarUrl": "",
    "googlePlusUrl": "",
    "pinterestUrl": "",
    "tumblrUrl": "",
    "vimeoUrl": ""
  },
  "primaryContact": {
    "id": "c3563aa1-b27a-4bea-838a-523ba1893443",
    "firstName": "Jefferson",
    "lastName": "Ortega",
    "preferredFirstName": null,
    "primaryEmailAddress": "jefferson_ortega@berkeley.edu",
    "profileImageFilePath": null,
    "institutionId": 1660,
    "privacy": "Unselected"
  },
  "primaryContactId": {
    "communityMemberId": 31515040,
    "accountId": "c3563aa1-b27a-4bea-838a-523ba1893443",
    "campusEmail": "jefferson_ortega@berkeley.edu"
  },
  "contactInfo": [
    {
      "id": 169156,
      "addressType": 0,
      "phoneNumber": null,
      "extension": null,
      "faxNumber": null,
      "street1": null,
      "street2": null,
      "city": null,
      "state": null,
      "zip": null,
      "country": null,
      "deleted": false
    }
  ],
  "organizationType": {
    "id": 1243,
    "branchId": 45852,
    "name": "Registered Student Organizations",
    "showMembersToPublic": false,
    "showOfficersToPublic": false,
    "showMembersToLoggedInUsersByDefault": false,
    "showOfficersToLoggedInUsersByDefault": false,
    "autoApproveRequests": false,
    "eventsEnabled": true,
    "serviceHoursEnabled": true,
    "financeEnabled": true,
    "financeRequestsEnabled": true,
    "fundingRequestsEnabled": true,
    "purchaseRequestsEnabled": true,
    "budgetingEnabled": false,
    "budgetingRequestsEnabled": false,
    "electionsEnabled": true,
    "formsEnabled": true,
    "galleryEnabled": true,
    "outcomesEnabled": true,
    "rosterEnabled": true,
    "documentsEnabled": true,
    "shownInPublicDirectory": true,
    "isSystemType": false,
    "adminOnly": false,
    "isClosed": false,
    "reRegistrationAvailabilty": null
  },
  "categories": [],
  "submissions": [],
  "coverPhoto": {
    "id": 0,
    "imageId": "",
    "imagePath": "",
    "url": "",
    "thumbnailUrl": "",
    "caption": "",
    "dateCreated": "",
    "institutionId": 0
  },
  "imageServerBaseUrl": "",
  "baseUrl": "https://callink.berkeley.edu"
}