{
  "id": 85779,
  "institutionId": 1660,
  "parentOrganizationId": null,
  "branchId": null,
  "name": "VISION 💙",
  "shortName": "VISION",
  "websiteKey": "vision",
  "profilePicture": "597d0e37-7338-4342-8fd3-32ca93ac8d0622c32c19-d093-4b11-8f22-8a5dd3230fbd.jpg",
  "profilePictureURL": "https://se-images.campuslabs.com/clink/images/597d0e37-7338-4342-8fd3-32ca93ac8d0622c32c19-d093-4b11-8f22-8a5dd3230fbd.jpg",
  "description": "\u003cp\u003eVISION, a mentorship program under Vietnamese Student Association at the University of California, Berkeley, recognizes and understands the significance of the historical, cultural and contemporary issues the Vietnamese and Vietnamese American communities face. VISION aims to foster and encourage high school students to take away what they learn and gain from our program to become leaders of their own communities. Fundamentally, VISION empowers students to embrace their individual identities as well as the heritage of the Vietnamese culture.\u003c/p\u003e\r\n\u003cp\u003e\u0026nbsp;\u003c/p\u003e\r\n\u003cp\u003e\u0026nbsp;\u003c/p\u003e",
  "summary": "VISION is a 4-day, 3-night mentorship program aimed at bringing awareness to historical, cultural and contemporary Vietnamese and Vietnamese American issues.",
  "categoryIds": [
    "5104",
    "7850",
    "18659"
  ],
  "categoryNames": [
    "Cultural \u0026 Identity/International Student Organizations",
    "Undergraduate Organizations",
    "Blue Heart Initiative Category"
  ],
  "status": "Active",
  "visibility": "Public",
  "email": "outreach@calvsa.com",
  "communityId": 219,
  "nameSortKey": "V",
  "comment": null,
  "showJoin": false,
  "statusChangeDateTime": "2014-01-24T15:13:55-05:00",
  "startDate": "2013-05-28T00:00:00-04:00",
  "endDate": null,
  "parentId": 45852,
  "wallId": null,
  "discussionId": 1235331,
  "groupTypeId": null,
  "organizationTypeId": 1243,
  "cssConfigurationId": null,
  "deleted": false,
  "enableGoogleCalendar": false,
  "modifiedOn": "2025-02-28T14:32:56-05:00",
  "showFacebookWall": false,
  "showTwitterFeed": false,
  "isShownInPublicDirectory": true,
  "isAdminOnly": false,
  "isBranch": false,
  "legacyKey": null,
  "parentLegacyKey": null,
  "legacyPrimaryContactKey": null,
  "socialMedia": {
    "externalWebsite": "http://www.calvsa.com/vision",
    "facebookUrl": "http://www.facebook.com/CalVSAVISION",
    "twitterUrl": "",
    "twitterUserName": null,
    "instagramUrl": "https://www.instagram.com/calvsa.vision/",
    "linkedInUrl": "",
    "youtubeUrl": "",
    "flickrUrl": "",
    "googleCalendarUrl": "",
    "googlePlusUrl": "",
    "pinterestUrl": "",
    "tumblrUrl": "",
    "vimeoUrl": ""
  },
  "primaryContact": {
    "id": "bf91d0e9-811c-4c78-8109-9701c6dd6d10",
    "firstName": "Cam-Truc",
    "lastName": "Hua Di",
    "preferredFirstName": null,
    "primaryEmailAddress": "cthuadi@berkeley.edu",
    "profileImageFilePath": null,
    "institutionId": 1660,
    "privacy": "Unselected"
  },
  "primaryContactId": {
    "communityMemberId": 38421772,
    "accountId": "bf91d0e9-811c-4c78-8109-9701c6dd6d10",
    "campusEmail": "cthuadi@berkeley.edu"
  },
  "contactInfo": [
    {
      "id": 163313,
      "addressType": 0,
      "phoneNumber": null,
      "extension": null,
      "faxNumber": null,
      "street1": "ASUC c/o VISION",
      "street2": "112 Hearst Gym",
      "city": "Berkeley",
      "state": "CA",
      "zip": "94720",
      "country": "USA",
      "deleted": false
    }
  ],
  "organizationType": {
    "id": 1243,
    "branchId": 45852,
    "name": "Registered Student Organizations",
    "showMembersToPublic": false,
    "showOfficersToPublic": false,
    "showMembersToLoggedInUsersByDefault": false,
    "showOfficersToLoggedInUsersByDefault": false,
    "autoApproveRequests": false,
    "eventsEnabled": true,
    "serviceHoursEnabled": true,
    "financeEnabled": true,
    "financeRequestsEnabled": true,
    "fundingRequestsEnabled": true,
    "purchaseRequestsEnabled": true,
    "budgetingEnabled": false,
    "budgetingRequestsEnabled": false,
    "electionsEnabled": true,
    "formsEnabled": true,
    "galleryEnabled": true,
    "outcomesEnabled": true,
    "rosterEnabled": true,
    "documentsEnabled": true,
    "shownInPublicDirectory": true,
    "isSystemType": false,
    "adminOnly": false,
    "isClosed": false,
    "reRegistrationAvailabilty": null
  },
  "categories": [],
  "submissions": [],
  "coverPhoto": {
    "id": 0,
    "imageId": "",
    "imagePath": "",
    "url": "",
    "thumbnailUrl": "",
    "caption": "",
    "dateCreated": "",
    "institutionId": 0
  },
  "imageServerBaseUrl": "",
  "baseUrl": "https://callink.berkeley.edu"
}